tucha_test_new_package/__init__.py
tucha_test_new_package/api.py
tucha_test_new_package/exceptions.py
tucha_test_new_package/request.py
tucha_test_new_package/Handlers/__init__.py
tucha_test_new_package/Handlers/standard.py
tucha_test_new_package/Handlers/transfer.py
tucha_test_new_package/Handlers/utils.py
tucha_test_new_package-1.0.0.dist-info/LICENSE
tucha_test_new_package-1.0.0.dist-info/METADATA
tucha_test_new_package-1.0.0.dist-info/WHEEL
tucha_test_new_package-1.0.0.dist-info/top_level.txt
tucha_test_new_package-1.0.0.dist-info/RECORD
