Metadata-Version: 2.1
Name: tucha-test-new-package
Version: 1.0.0
Summary: Test tucha package
Home-page: https://github.com/maloi56/tucha_test_new_package
Author: Tucha
Author-email: beztfake@yandex.ru
License: MIT
Classifier: Programming Language :: Python :: 3
Classifier: License :: OSI Approved :: MIT License
Classifier: Operating System :: OS Independent
Requires-Python: >=3.6
License-File: LICENSE
Requires-Dist: requests
